medication_management/__init__.py
medication_management/inventory.py
medication_management/medication.py
medication_management/prescription.py
user_management/__init__.py
user_management/family.py
user_management/reminder.py
FamilyMedT-0.1.0.dist-info/LICENSE.txt
FamilyMedT-0.1.0.dist-info/METADATA
FamilyMedT-0.1.0.dist-info/WHEEL
FamilyMedT-0.1.0.dist-info/top_level.txt
FamilyMedT-0.1.0.dist-info/RECORD
