Metadata-Version: 2.1
Name: FamilyMedT
Version: 0.1.0
Summary: A tool to manage family medication and users
Author-email: Yuzhou Wang and Yubo Wang <wyuzhou@outlook.com>
License: MIT
Project-URL: Homepage, https://github.com/wyuzhou6/Data533-project-step3.git
Classifier: Programming Language :: Python :: 3
Classifier: License :: OSI Approved :: MIT License
Classifier: Operating System :: OS Independent
License-File: LICENSE.txt
